MolBokeh/MolBokeh.py
MolBokeh/__init__.py
MolBokeh/__main__.py
MolBokeh-1.0.1.dist-info/LICENSE
MolBokeh-1.0.1.dist-info/METADATA
MolBokeh-1.0.1.dist-info/WHEEL
MolBokeh-1.0.1.dist-info/top_level.txt
MolBokeh-1.0.1.dist-info/RECORD
