Metadata-Version: 2.1
Name: MolBokeh
Version: 1.0.1
Summary: Simple package to display molecules images in bokeh interactive charts.
Home-page: https://github.com/jeffrichardchemistry/molbokeh
Author: Jefferson Richard
Author-email: jrichardquimica@gmail.com
License: MIT
Keywords: Cheminformatics,Chemistry,QSAR,QSPR,Molecular visualization,Molecular plot,bokeh plot
Classifier: Intended Audience :: Developers
Classifier: Intended Audience :: Science/Research
Classifier: Topic :: Scientific/Engineering :: Chemistry
Classifier: Topic :: Scientific/Engineering :: Physics
Classifier: Topic :: Scientific/Engineering :: Bio-Informatics
Classifier: Topic :: Scientific/Engineering
Classifier: License :: OSI Approved :: MIT License
Classifier: Natural Language :: English
Classifier: Operating System :: Microsoft :: Windows
Classifier: Operating System :: POSIX :: Linux
Classifier: Environment :: MacOS X
Classifier: Programming Language :: Python :: 3.6
Classifier: Programming Language :: Python :: 3.8
Classifier: Programming Language :: Python :: 3.9
Classifier: Programming Language :: Python :: 3.10
License-File: LICENSE
Requires-Dist: pandas
Requires-Dist: bokeh
Requires-Dist: rdkit
